mess/__init__.py
mess/prepare_all_datasets.py
mess/datasets/MMSegDataset.py
mess/datasets/TorchvisionDataset.py
mess/datasets/__init__.py
mess/datasets/register_TEMPLATE.py
mess/datasets/register_atlantis.py
mess/datasets/register_bdd100k.py
mess/datasets/register_chase_db1.py
mess/datasets/register_corrosion_cs.py
mess/datasets/register_cryonuseg.py
mess/datasets/register_cub_200.py
mess/datasets/register_cwfid.py
mess/datasets/register_dark_zurich.py
mess/datasets/register_deepcrack.py
mess/datasets/register_dram.py
mess/datasets/register_floodnet.py
mess/datasets/register_foodseg.py
mess/datasets/register_isaid.py
mess/datasets/register_isprs_potsdam.py
mess/datasets/register_kvasir_instrument.py
mess/datasets/register_mhp_v1.py
mess/datasets/register_paxray.py
mess/datasets/register_pst900.py
mess/datasets/register_suim.py
mess/datasets/register_uavid.py
mess/datasets/register_worldfloods.py
mess/datasets/register_zerowaste.py
mess/evaluation/__init__.py
mess/evaluation/mess_evaluation.py
mess/evaluation/sem_seg_evaluation.py
mess/in_domain/README.md
mess/in_domain/__init__.py
mess/in_domain/eval.sh
mess/in_domain/in_domain_evaluation.py
mess/in_domain/prepare_in_domain_datasets.py
mess/in_domain/datasets/__init__.py
mess/in_domain/datasets/register_ade20k_full.py
mess/in_domain/datasets/register_pascal_context.py
mess/in_domain/datasets/register_pascal_voc.py
mess/in_domain/prepare_datasets/__init__.py
mess/in_domain/prepare_datasets/prepare_ade20k_full_sem_seg.py
mess/in_domain/prepare_datasets/prepare_ade20k_sem_seg.py
mess/in_domain/prepare_datasets/prepare_pascal_context_459.py
mess/in_domain/prepare_datasets/prepare_pascal_context_59.py
mess/in_domain/prepare_datasets/prepare_pascal_voc.py
mess/prepare_datasets/__init__.py
mess/prepare_datasets/prepare_TEMPLATE.py
mess/prepare_datasets/prepare_atlantis.py
mess/prepare_datasets/prepare_bdd100k.py
mess/prepare_datasets/prepare_chase_db1.py
mess/prepare_datasets/prepare_corrosion_cs.py
mess_benchmark-0.2.dist-info/LICENSE
mess_benchmark-0.2.dist-info/METADATA
mess_benchmark-0.2.dist-info/WHEEL
mess_benchmark-0.2.dist-info/top_level.txt
mess_benchmark-0.2.dist-info/RECORD
