Metadata-Version: 2.1
Name: mess-benchmark
Version: 0.2
Summary: MESS – Multi-domain Evaluation of Semantic Segmentation
Author-email: Benedikt Blumenstiel <benedikt.blumenstiel@live.com>
Project-URL: Homepage, https://blumenstiel.github.io/mess-benchmark/
Project-URL: Bug Tracker, https://github.com/blumenstiel/MESS/issues
Keywords: mess,benchmark,zero-shot,evaluation
Classifier: Programming Language :: Python :: 3
Classifier: License :: OSI Approved :: MIT License
Classifier: Operating System :: OS Independent
Requires-Python: >=3.8
License-File: LICENSE
Requires-Dist: torch >=1.10.1
Requires-Dist: torchvision >=0.11.2
Requires-Dist: pandas >=1.5.1
Requires-Dist: numpy >=1.22.4
Requires-Dist: rasterio >=1.3.4
Requires-Dist: gdown >=4.6.4
Requires-Dist: opencv-python-headless >=4.7.0.72
Requires-Dist: iopath >=0.1.7
Requires-Dist: Pillow >=7.1
Requires-Dist: tqdm >=4.64.1
Requires-Dist: matplotlib >=3.6.2
Provides-Extra: all
Requires-Dist: scipy ; extra == 'all'
Requires-Dist: pycocotools ; extra == 'all'
